README.rst
setup.py
subpop.yaml
bin/boxer
boxer/__init__.py
boxer/common.py
boxer/context.py
boxer/model.py
boxer/pretty_logging.py
boxer/config/__init__.py
boxer/config/base.py
funtoo/containers/docker.py
funtoo/containers/generate.py
funtoo/containers/singularity.py
funtoo_boxer.egg-info/PKG-INFO
funtoo_boxer.egg-info/SOURCES.txt
funtoo_boxer.egg-info/dependency_links.txt
funtoo_boxer.egg-info/requires.txt
funtoo_boxer.egg-info/top_level.txt