Metadata-Version: 2.1
Name: funtoo-boxer
Version: 1.0.3
Summary: Funtoo framework for container generation.
Home-page: https://code.funtoo.org/bitbucket/users/drobbins/repos/funtoo-boxer/browse
Author: Daniel Robbins
Author-email: drobbins@funtoo.org
Classifier: Programming Language :: Python :: 3
Classifier: License :: OSI Approved :: Apache Software License
Classifier: Operating System :: POSIX :: Linux
Requires-Python: >=3.7
